pytorch_cinic/__init__.py
pytorch_cinic/dataset.py
pytorch_cinic-0.0.6.dist-info/LICENSE
pytorch_cinic-0.0.6.dist-info/METADATA
pytorch_cinic-0.0.6.dist-info/WHEEL
pytorch_cinic-0.0.6.dist-info/top_level.txt
pytorch_cinic-0.0.6.dist-info/RECORD
