Metadata-Version: 2.1
Name: pytorch-cinic
Version: 0.0.6
Summary: A small wrapper around the CINIC10 dataset https://datashare.ed.ac.uk/handle/10283/3192
Author-email: Igor Krawczuk <contact-gh@krawczuk.eu>
License: MIT License        
Project-URL: Homepage, https://github.com/igor-krawczuk/pytorch-cinic
Project-URL: Bug Tracker, https://github.com/igor-krawczuk/pytorch-cinic/issues
Classifier: Programming Language :: Python :: 3
Classifier: License :: OSI Approved :: MIT License
Classifier: Operating System :: OS Independent
License-File: LICENSE
Requires-Dist: wget
Requires-Dist: torch
Requires-Dist: torchvision
